kpplus/__init__.py
kpplus/kpplus.py
kpplus-0.0.3.dist-info/LICENSE
kpplus-0.0.3.dist-info/METADATA
kpplus-0.0.3.dist-info/WHEEL
kpplus-0.0.3.dist-info/top_level.txt
kpplus-0.0.3.dist-info/RECORD
