Metadata-Version: 2.1
Name: kpplus
Version: 0.0.3
Summary: A JIT optimized K-Prototype algorithm
Home-page: https://github.com/youbao88/KPrototypes_plus
Author: Minhao Zhou
Author-email: youbao2@hotmail.com
License: UNKNOWN
Platform: UNKNOWN
Classifier: Programming Language :: Python :: 3
Classifier: License :: OSI Approved :: MIT License
Classifier: Operating System :: OS Independent
License-File: LICENSE
Requires-Dist: pandas
Requires-Dist: numpy
Requires-Dist: numba
Requires-Dist: joblib
